kraken_llm/__init__.py
kraken_llm/client/__init__.py
kraken_llm/client/adaptive.py
kraken_llm/client/asr.py
kraken_llm/client/base.py
kraken_llm/client/completion.py
kraken_llm/client/embeddings.py
kraken_llm/client/factory.py
kraken_llm/client/multimodal.py
kraken_llm/client/reasoning.py
kraken_llm/client/standard.py
kraken_llm/client/streaming.py
kraken_llm/client/structured.py
kraken_llm/client/universal.py
kraken_llm/confidence/__init__.py
kraken_llm/confidence/filter.py
kraken_llm/confidence/metrics.py
kraken_llm/config/__init__.py
kraken_llm/config/defaults.py
kraken_llm/config/settings.py
kraken_llm/exceptions/__init__.py
kraken_llm/exceptions/api.py
kraken_llm/exceptions/base.py
kraken_llm/exceptions/network.py
kraken_llm/exceptions/validation.py
kraken_llm/models/__init__.py
kraken_llm/models/requests.py
kraken_llm/models/responses.py
kraken_llm/models/streaming.py
kraken_llm/models/tools.py
kraken_llm/streaming/__init__.py
kraken_llm/streaming/handler.py
kraken_llm/streaming/repair.py
kraken_llm/structured/__init__.py
kraken_llm/structured/validator.py
kraken_llm/tools/__init__.py
kraken_llm/tools/executor.py
kraken_llm/tools/functions.py
kraken_llm/tools/tools.py
kraken_llm/utils/__init__.py
kraken_llm/utils/color.py
kraken_llm/utils/logging.py
kraken_llm/utils/media.py
kraken_llm-0.1.5.dist-info/METADATA
kraken_llm-0.1.5.dist-info/WHEEL
kraken_llm-0.1.5.dist-info/licenses/LICENSE
kraken_llm-0.1.5.dist-info/RECORD
