Metadata-Version: 2.4
Name: kraken_llm
Version: 0.1.5
Summary: Universal LLM framework with full OpenAI API support
Project-URL: Homepage, https://github.com/antonshalin76/kraken_llm
Project-URL: Repository, https://github.com/antonshalin76/kraken_llm
Project-URL: Issues, https://github.com/antonshalin76/kraken_llm/issues
Author-email: Anton Shalin <anton.shalin@gmail.com>
License: MIT License
License-File: LICENSE
Keywords: ai,async,llm,machine-learning,openai,streaming
Classifier: Development Status :: 3 - Alpha
Classifier: Intended Audience :: Developers
Classifier: License :: OSI Approved :: MIT License
Classifier: Programming Language :: Python :: 3
Classifier: Programming Language :: Python :: 3.10
Classifier: Programming Language :: Python :: 3.11
Classifier: Programming Language :: Python :: 3.12
Classifier: Topic :: Scientific/Engineering :: Artificial Intelligence
Classifier: Topic :: Software Development :: Libraries :: Python Modules
Requires-Python: >=3.10
Requires-Dist: httpx
Requires-Dist: numpy
Requires-Dist: openai
Requires-Dist: outlines
Requires-Dist: pillow
Requires-Dist: pydantic
Requires-Dist: pydantic-settings
Requires-Dist: python-dotenv
Requires-Dist: typing-extensions
Provides-Extra: demo
Requires-Dist: fastapi; extra == 'demo'
Requires-Dist: uvicorn; extra == 'demo'
Provides-Extra: dev
Requires-Dist: black; extra == 'dev'
Requires-Dist: coverage; extra == 'dev'
Requires-Dist: isort; extra == 'dev'
Requires-Dist: mypy; extra == 'dev'
Requires-Dist: pytest; extra == 'dev'
Requires-Dist: pytest-asyncio; extra == 'dev'
Requires-Dist: pytest-mock; extra == 'dev'
